model_w/env_manager/__init__.py
model_w/env_manager/_dotenv.py
model_w/env_manager/_exceptions.py
model_w/env_manager/_manager.py
model_w/env_manager/_preset.py
model_w/env_manager/_utils.py
model_w/env_manager/py.typed
modelw_env_manager-1.0.0.dist-info/LICENSE
modelw_env_manager-1.0.0.dist-info/METADATA
modelw_env_manager-1.0.0.dist-info/WHEEL
modelw_env_manager-1.0.0.dist-info/RECORD
